sluggi/__init__.py
sluggi/api.py
sluggi/cli.py
sluggi/constants.py
sluggi/replacements.py
sluggi/utils.py
sluggi-0.1.2.dist-info/licenses/LICENSE
sluggi-0.1.2.dist-info/METADATA
sluggi-0.1.2.dist-info/WHEEL
sluggi-0.1.2.dist-info/entry_points.txt
sluggi-0.1.2.dist-info/top_level.txt
sluggi-0.1.2.dist-info/RECORD
