Metadata-Version: 2.4
Name: sluggi
Version: 0.1.2
Summary: A modern, high-performance Python library for turning text into clean, URL-safe slugs.
Author: atillaguzel
License: MIT
Project-URL: Homepage, https://github.com/blip-box/sluggi
Project-URL: Repository, https://github.com/blip-box/sluggi
Project-URL: Documentation, https://github.com/blip-box/sluggi#readme
Project-URL: Changelog, https://github.com/blip-box/sluggi/releases
Project-URL: Issues, https://github.com/blip-box/sluggi/issues
Keywords: slug,slugify,url,text,python,unicode,transliteration,cli
Classifier: Programming Language :: Python :: 3
Classifier: Programming Language :: Python :: 3.9
Classifier: Programming Language :: Python :: 3.10
Classifier: Programming Language :: Python :: 3.11
Classifier: Programming Language :: Python :: 3.12
Classifier: Programming Language :: Python :: 3.13
Classifier: Intended Audience :: Developers
Classifier: Topic :: Software Development :: Libraries :: Python Modules
Classifier: Topic :: Text Processing :: Linguistic
Classifier: Operating System :: OS Independent
Classifier: Natural Language :: English
Requires-Python: >=3.9
License-File: LICENSE
Provides-Extra: test
Requires-Dist: pytest>=8.4.0; extra == "test"
Requires-Dist: pytest-cov>=6.1.1; extra == "test"
Requires-Dist: hypothesis>=6.131.25; extra == "test"
Requires-Dist: pytest-asyncio>=1.0.0; extra == "test"
Provides-Extra: cli
Requires-Dist: typer>=0.9; extra == "cli"
Requires-Dist: rich>=13.0; extra == "cli"
Provides-Extra: dev
Requires-Dist: black>=25.1.0; extra == "dev"
Requires-Dist: pre-commit>=4.2.0; extra == "dev"
Requires-Dist: ruff>=0.11.2; extra == "dev"
Requires-Dist: mutmut>=3.3.0; extra == "dev"
Requires-Dist: requests>=2.31.0; extra == "dev"
Requires-Dist: python-slugify>=8.0.4; extra == "dev"
Provides-Extra: emoji
Requires-Dist: emoji>=2.14.1; extra == "emoji"
Dynamic: license-file
